event_channel/__init__.py
event_channel/event_channel.py
event_channel/threaded_event_channel.py
event_channel-0.4.3.dist-info/LICENSE
event_channel-0.4.3.dist-info/METADATA
event_channel-0.4.3.dist-info/WHEEL
event_channel-0.4.3.dist-info/top_level.txt
event_channel-0.4.3.dist-info/RECORD
