Metadata-Version: 2.1
Name: event_channel
Version: 0.4.3
Summary: Pub sub implementation
Home-page: https://github.com/mandrewcito/event_channel
Author: mandrewcito
Author-email: anbaalo@gmail.com
License: UNKNOWN
Keywords: publish subscribe
Platform: UNKNOWN
Classifier: Programming Language :: Python :: 3
Classifier: Operating System :: OS Independent
License-File: LICENSE
